MethodicConfigurator/ArduPilot_icon.png
MethodicConfigurator/ArduPilot_logo.png
MethodicConfigurator/__init__.py
MethodicConfigurator/annotate_params.py
MethodicConfigurator/ardupilot_methodic_configurator.py
MethodicConfigurator/argparse_check_range.py
MethodicConfigurator/backend_filesystem.py
MethodicConfigurator/backend_filesystem_configuration_steps.py
MethodicConfigurator/backend_filesystem_program_settings.py
MethodicConfigurator/backend_filesystem_vehicle_components.py
MethodicConfigurator/backend_flightcontroller.py
MethodicConfigurator/backend_flightcontroller_info.py
MethodicConfigurator/backend_mavftp.py
MethodicConfigurator/battery_cell_voltages.py
MethodicConfigurator/common_arguments.py
MethodicConfigurator/configuration_steps_ArduCopter.json
MethodicConfigurator/configuration_steps_ArduPlane.json
MethodicConfigurator/configuration_steps_Heli.json
MethodicConfigurator/configuration_steps_Rover.json
MethodicConfigurator/extract_param_defaults.py
MethodicConfigurator/frontend_tkinter_base.py
MethodicConfigurator/frontend_tkinter_component_editor.py
MethodicConfigurator/frontend_tkinter_component_editor_base.py
MethodicConfigurator/frontend_tkinter_connection_selection.py
MethodicConfigurator/frontend_tkinter_directory_selection.py
MethodicConfigurator/frontend_tkinter_entry_dynamic.py
MethodicConfigurator/frontend_tkinter_flightcontroller_info.py
MethodicConfigurator/frontend_tkinter_pair_tuple_combobox.py
MethodicConfigurator/frontend_tkinter_parameter_editor.py
MethodicConfigurator/frontend_tkinter_parameter_editor_documentation_frame.py
MethodicConfigurator/frontend_tkinter_parameter_editor_table.py
MethodicConfigurator/frontend_tkinter_template_overview.py
MethodicConfigurator/internationalization.py
MethodicConfigurator/mavftp_example.py
MethodicConfigurator/middleware_fc_ids.py
MethodicConfigurator/middleware_template_overview.py
MethodicConfigurator/param_pid_adjustment_update.py
MethodicConfigurator/tempcal_imu.py
MethodicConfigurator-0.9.16.dist-info/LICENSE.md
MethodicConfigurator-0.9.16.dist-info/METADATA
MethodicConfigurator-0.9.16.dist-info/WHEEL
MethodicConfigurator-0.9.16.dist-info/entry_points.txt
MethodicConfigurator-0.9.16.dist-info/top_level.txt
MethodicConfigurator-0.9.16.dist-info/RECORD
