Metadata-Version: 2.1
Name: MethodicConfigurator
Version: 0.9.16
Summary: A clear configuration sequence for ArduPilot vehicles
Author-email: Amilcar do Carmo Lucas <amilcar.lucas@iav.de>
Maintainer-email: Amilcar do Carmo Lucas <amilcar.lucas@iav.de>
License: GPLv3
Project-URL: homepage, https://github.com/ArduPilot/MethodicConfigurator
Project-URL: documentation, https://github.com/ArduPilot/MethodicConfigurator/blob/master/USERMANUAL.md
Project-URL: issues, https://github.com/ArduPilot/MethodicConfigurator/issues
Project-URL: source, https://github.com/ArduPilot/MethodicConfigurator
Project-URL: forum, https://discuss.ardupilot.org/t/new-ardupilot-methodic-configurator-gui/115038/
Project-URL: chat, https://discord.com/invite/ArduPilot
Project-URL: download, https://github.com/ArduPilot/MethodicConfigurator/releases
Project-URL: changelog, https://github.com/ArduPilot/MethodicConfigurator/releases
Keywords: ArduPilot,Configuration,SCM,Methodic,ArduCopter,ArduPlane,ArduRover,ArduSub
Classifier: Development Status :: 4 - Beta
Classifier: Intended Audience :: Science/Research
Classifier: License :: OSI Approved :: GNU General Public License v3 (GPLv3)
Classifier: Operating System :: OS Independent
Classifier: Programming Language :: Python :: 3.9
Classifier: Programming Language :: Python :: 3.10
Classifier: Programming Language :: Python :: 3.11
Classifier: Programming Language :: Python :: 3.12
Classifier: Topic :: Scientific/Engineering
Requires-Python: >=3.9
License-File: LICENSE.md
Requires-Dist: defusedxml
Requires-Dist: matplotlib
Requires-Dist: numpy
Requires-Dist: platformdirs
Requires-Dist: pymavlink
Requires-Dist: pyserial
Requires-Dist: pillow
Requires-Dist: setuptools
Requires-Dist: requests
Provides-Extra: dev
Requires-Dist: ruff; extra == "dev"
Requires-Dist: pre-commit; extra == "dev"
Requires-Dist: pytest; extra == "dev"
Requires-Dist: pytest-cov; extra == "dev"
Requires-Dist: coverage; extra == "dev"
Requires-Dist: mock; extra == "dev"
